renderapi/__init__.py
renderapi/base_resource.py
renderapi/config.py
renderapi/custom_domains.py
renderapi/custom_requests.py
renderapi/exceptions.py
renderapi/jobs.py
renderapi/owners.py
renderapi/renderapi.py
renderapi-1.1.0.dist-info/LICENSE
renderapi-1.1.0.dist-info/METADATA
renderapi-1.1.0.dist-info/WHEEL
renderapi-1.1.0.dist-info/top_level.txt
renderapi-1.1.0.dist-info/RECORD
