Metadata-Version: 2.1
Name: renderapi
Version: 1.1.0
Summary: render.com API wrapper
Home-page: https://github.com/abrihter/renderapi/releases
Author: bojan
Author-email: 
License: MIT
Download-URL: https://github.com/abrihter/renderapi/archive/v_110.tar.gz
Keywords: RENDER.COM,API,WRAPPER
Platform: UNKNOWN
Classifier: Development Status :: 5 - Production/Stable
Classifier: Intended Audience :: Developers
Classifier: Topic :: Software Development :: Build Tools
Classifier: License :: OSI Approved :: MIT License
Classifier: Programming Language :: Python :: 3
License-File: LICENSE
